<?xml version="1.0"?>
<restricciones xmlns:xsi="http://www.w3.org/2001/XMLSchema-instance"
xsi:noNamespaceSchemaLocation="restricciones.xsd">

<!--Primer ejercicio. Número de teléfono.-->
    <telefono>+34667860076</telefono>

<!--Segundo ejercicio. Patrón para poner un password entre 5 y 8 caracteres con mayúsculas, minúsculas y números-->
    <password>Basa2bjg</password>

<!--Tercer ejercicio. Patrón para el DNI 30101010A-->

    <dni>30101010A</dni>

<!--Cuarto ejercicio. Patrón para coincidencia con cualquier palabra o frase de la lista siguiente:
tontería
maldito
caray
caramba
madre mía
ostras
-->

    <coincidencia>caramba</coincidencia>

<!--Quinto ejercicio. Patrón para coincidencia con la palabra "viagra" y con algunas de las alteraciones que utilizan los emisores de spam, por ejemplo:
vi@gra
v1agra
v1@gra
v!@gr@
-->

    <viagra>viagra</viagra>

<!--Sexto ejercicio. Patrón para correo electrónico, por ejemplo: pepe87@gmail.com-->

    <correo>pepe87@gmail.com</correo>


<!--Ejercicio complexType con restricciones
mujer: f, F, Mujer, M
hombre: m, M, Hombre, H-->

    <sexo>
        <mujer>Mujer</mujer>
        <hombre>Hombre</hombre>
    </sexo>

</restricciones>